pegpog/__init__.py
pegpog/api.py
pegpog/errors.py
pegpog/grammar.py
pegpog/parser.py
pegpog/peg.py
pegpog/rule.py
pegpog/util.py
pegpog-0.1.dist-info/LICENSE
pegpog-0.1.dist-info/METADATA
pegpog-0.1.dist-info/WHEEL
pegpog-0.1.dist-info/top_level.txt
pegpog-0.1.dist-info/RECORD
