Metadata-Version: 2.1
Name: pegpog
Version: 0.1
Summary: Parse strings
Home-page: https://github.com/GeeTransit/pegpog
Author: George Zhang
Author-email: geetransit@gmail.com
License: MIT
Platform: UNKNOWN
Classifier: Development Status :: 3 - Alpha
Classifier: License :: OSI Approved :: MIT License
Classifier: Operating System :: OS Independent
Classifier: Programming Language :: Python :: 3
Classifier: Programming Language :: Python :: 3.9
Classifier: Topic :: Text Processing :: General
License-File: LICENSE
